pingouin/__init__.py
pingouin/bayesian.py
pingouin/circular.py
pingouin/config.py
pingouin/contingency.py
pingouin/correlation.py
pingouin/distribution.py
pingouin/effsize.py
pingouin/equivalence.py
pingouin/multicomp.py
pingouin/multivariate.py
pingouin/nonparametric.py
pingouin/pairwise.py
pingouin/parametric.py
pingouin/plotting.py
pingouin/power.py
pingouin/regression.py
pingouin/reliability.py
pingouin/utils.py
pingouin/datasets/__init__.py
pingouin/datasets/ancova.csv
pingouin/datasets/anova.csv
pingouin/datasets/anova2.csv
pingouin/datasets/anova2_unbalanced.csv
pingouin/datasets/anova3.csv
pingouin/datasets/anova3_unbalanced.csv
pingouin/datasets/blandaltman.csv
pingouin/datasets/chi2_independence.csv
pingouin/datasets/chi2_mcnemar.csv
pingouin/datasets/circular.csv
pingouin/datasets/cochran.csv
pingouin/datasets/cronbach_alpha.csv
pingouin/datasets/cronbach_wide_missing.csv
pingouin/datasets/datasets.csv
pingouin/datasets/icc.csv
pingouin/datasets/mediation.csv
pingouin/datasets/mixed_anova.csv
pingouin/datasets/mixed_anova_unbalanced.csv
pingouin/datasets/multivariate.csv
pingouin/datasets/pairwise_corr.csv
pingouin/datasets/pairwise_tests.csv
pingouin/datasets/pairwise_tests_missing.csv
pingouin/datasets/partial_corr.csv
pingouin/datasets/penguins.csv
pingouin/datasets/rm_anova.csv
pingouin/datasets/rm_anova2.csv
pingouin/datasets/rm_anova_wide.csv
pingouin/datasets/rm_corr.csv
pingouin/datasets/rm_missing.csv
pingouin/datasets/tips.csv
pingouin-0.5.5.dist-info/LICENSE
pingouin-0.5.5.dist-info/METADATA
pingouin-0.5.5.dist-info/WHEEL
pingouin-0.5.5.dist-info/top_level.txt
pingouin-0.5.5.dist-info/RECORD
