Metadata-Version: 2.1
Name: pingouin
Version: 0.5.5
Summary: Pingouin: statistical package for Python
Author-email: Raphael Vallat <raphaelvallat9@gmail.com>
Maintainer-email: Raphael Vallat <raphaelvallat9@gmail.com>
License: GPL-3.0
Project-URL: Homepage, https://pingouin-stats.org/index.html
Project-URL: Downloads, https://github.com/raphaelvallat/pingouin/
Classifier: Intended Audience :: Science/Research
Classifier: Operating System :: MacOS
Classifier: Operating System :: POSIX
Classifier: Operating System :: Unix
Classifier: Programming Language :: Python :: 3.10
Classifier: Programming Language :: Python :: 3.11
Classifier: Programming Language :: Python :: 3.8
Classifier: Programming Language :: Python :: 3.9
Classifier: Topic :: Scientific/Engineering :: Mathematics
Requires-Python: >=3.8
License-File: LICENSE
Requires-Dist: matplotlib
Requires-Dist: numpy
Requires-Dist: pandas>=1.5
Requires-Dist: pandas_flavor
Requires-Dist: scikit-learn>=1.2
Requires-Dist: scipy
Requires-Dist: seaborn
Requires-Dist: statsmodels
Requires-Dist: tabulate
Provides-Extra: test
Requires-Dist: pytest>=6; extra == "test"
Requires-Dist: pytest-cov; extra == "test"
Requires-Dist: codecov; extra == "test"
Requires-Dist: openpyxl; extra == "test"
Requires-Dist: mpmath; extra == "test"
Requires-Dist: coverage[toml]>=5.3; extra == "test"
Provides-Extra: docs
Requires-Dist: sphinx>7.0.0; extra == "docs"
Requires-Dist: pydata_sphinx_theme; extra == "docs"
Requires-Dist: numpydoc; extra == "docs"
Requires-Dist: sphinx-copybutton; extra == "docs"
Requires-Dist: sphinx-design; extra == "docs"
Requires-Dist: sphinx-notfound-page; extra == "docs"
